rxresume_mcp/__init__.py
rxresume_mcp/config.py
rxresume_mcp/main.py
rxresume_mcp/prompts.py
rxresume_mcp/resources.py
rxresume_mcp/rxresume_client.py
rxresume_mcp/server.py
rxresume_mcp/tools.py
rxresume_mcp/resources/api-endpoints.md
rxresume_mcp/resources/resume-schema.json
rxresume_mcp-0.0.2.dist-info/METADATA
rxresume_mcp-0.0.2.dist-info/WHEEL
rxresume_mcp-0.0.2.dist-info/entry_points.txt
rxresume_mcp-0.0.2.dist-info/licenses/LICENSE
rxresume_mcp-0.0.2.dist-info/RECORD
