Metadata-Version: 2.4
Name: rxresume-mcp
Version: 0.0.2
Summary: MCP Server for Reactive Resume
License-File: LICENSE
Requires-Python: >=3.11
Requires-Dist: attrs>=25.3.0
Requires-Dist: httpx>=0.28.1
Requires-Dist: jsonschema>=4.26.0
Requires-Dist: mcp>=1.25.0
Requires-Dist: pydantic>=2.11
Requires-Dist: python-dotenv>=1.0.1
Provides-Extra: dev
Requires-Dist: pytest-cov>=5.0.0; extra == 'dev'
Requires-Dist: pytest>=8.0.0; extra == 'dev'
Requires-Dist: ruff>=0.6.0; extra == 'dev'
